{
  "generated_by": "Primo TV - leite primo",
  "categories": [
    {
      "id": "brasil_abertos",
      "title": "Brasil - Abertos",
      "channels": [
        {
          "title": "TV Brasil (site)",
          "url": "https://play.ebc.com.br/",
          "tvg_id": "tvbrasil"
        },
        {
          "title": "TV Cultura (site)",
          "url": "https://culturaplay.tvcultura.com.br/channels/14",
          "tvg_id": "tvcultura"
        },
        {
          "title": "TV Câmara (embed)",
          "url": "https://www2.camara.leg.br/camaranoticias/tv/embedAoVivo.html",
          "tvg_id": "tvcamara"
        }
      ]
    },
    {
      "id": "noticias_internacionais",
      "title": "Internacional - Notícias",
      "channels": [
        {
          "title": "DW News (YouTube)",
          "url": "https://www.youtube.com/watch?v=LuKwFajn37U",
          "tvg_id": "dw"
        },
        {
          "title": "Euronews (site)",
          "url": "https://www.euronews.com/live",
          "tvg_id": "euronews"
        },
        {
          "title": "Al Jazeera English (site)",
          "url": "https://www.aljazeera.com/live/",
          "tvg_id": "aljazeera"
        }
      ]
    },
    {
      "id": "infantil",
      "title": "Infantil",
      "channels": [
        {
          "title": "PBS Kids (site)",
          "url": "https://pbskids.org/",
          "tvg_id": "pbskids"
        }
      ]
    },
    {
      "id": "esportes",
      "title": "Esportes",
      "channels": [
        {
          "title": "CBF TV (YouTube)",
          "url": "https://www.youtube.com/c/cbfnet",
          "tvg_id": "cbf"
        },
        {
          "title": "Red Bull TV",
          "url": "https://www.redbull.com/int-en/live",
          "tvg_id": "redbull"
        }
      ]
    }
  ]
}